colored_noise_sc.py
colored_noise_sc-0.2.0.dist-info/LICENSE
colored_noise_sc-0.2.0.dist-info/METADATA
colored_noise_sc-0.2.0.dist-info/WHEEL
colored_noise_sc-0.2.0.dist-info/top_level.txt
colored_noise_sc-0.2.0.dist-info/RECORD
