Metadata-Version: 2.1
Name: colored-noise-sc
Version: 0.2.0
Summary: An implementation of the sparse convolution algorithm (Lewis, 1989) for generating solid time-series of colored noise.
Author: Alexandre René
Maintainer: Alexandre René
License: MPL 2.0
Project-URL: Homepage, https://alcrene.github.io/colored-noise
Project-URL: Documentation, https://alcrene.github.io/colored-noise
Project-URL: Repository, https://github.com/alcrene/colored-noise
Project-URL: Issues, https://github.com/alcrene/colored-noise/issues
Keywords: noise,colored noise,sparse convolution,Perlin noise
Classifier: Development Status :: 4 - Beta
Classifier: Intended Audience :: Science/Research
Classifier: License :: OSI Approved :: Mozilla Public License 2.0 (MPL 2.0)
Classifier: Programming Language :: Python :: 3
Classifier: Programming Language :: Python :: 3.8
Classifier: Programming Language :: Python :: 3.9
Classifier: Programming Language :: Python :: 3.11
Classifier: Topic :: Scientific/Engineering :: Mathematics
Classifier: Topic :: Scientific/Engineering :: Physics
Requires-Python: >=3.8
License-File: LICENSE
Requires-Dist: numpy
Provides-Extra: docs
Requires-Dist: scipy ; extra == 'docs'
Requires-Dist: pint ; extra == 'docs'
Requires-Dist: holoviews ; extra == 'docs'
Requires-Dist: matplotlib ; extra == 'docs'
Requires-Dist: jupytext ; extra == 'docs'
Requires-Dist: jupyter-book ; extra == 'docs'
Provides-Extra: test
Requires-Dist: scipy ; extra == 'test'
Requires-Dist: pint ; extra == 'test'
Requires-Dist: holoviews ; extra == 'test'
Requires-Dist: scityping ; extra == 'test'
